sentry_wxwork/__init__.py
sentry_wxwork/plugin.py
sentry_wxwork_starit-1.0.9.dist-info/LICENSE
sentry_wxwork_starit-1.0.9.dist-info/METADATA
sentry_wxwork_starit-1.0.9.dist-info/WHEEL
sentry_wxwork_starit-1.0.9.dist-info/entry_points.txt
sentry_wxwork_starit-1.0.9.dist-info/top_level.txt
sentry_wxwork_starit-1.0.9.dist-info/RECORD
