Metadata-Version: 2.1
Name: sentry-wxwork-starit
Version: 1.0.9
Summary: A Sentry plugin which posts notifications to WxWork.
Home-page: http://gitlab.oa.com/sokos/sentry_wxwork_notification/
Author: Sokos Lee
Author-email: sokos@staritgp.com
License: MIT
Platform: UNKNOWN
Classifier: Intended Audience :: Developers
Classifier: Intended Audience :: System Administrators
Classifier: License :: OSI Approved :: MIT License
Classifier: Operating System :: OS Independent
Classifier: Topic :: Software Development
Classifier: Topic :: System :: Monitoring
License-File: LICENSE
Requires-Dist: sentry
